src/__init__.py
src/main.py
src/models/__init__.py
src/pipeline/__init__.py
src/pipeline/create_sample_image.py
src/pipeline/decrypt.py
src/pipeline/encrypt.py
src/pipeline/generate_key.py
src/pipeline/hindi_detection.py
src/pipeline/hindi_extraction.py
src/pipeline/ocr.py
src/pipeline/pii_detection.py
src/pipeline/process_new_files.py
src/pipeline/redaction.py
src/pipeline/utils.py
src/pipeline/workflow.py
src/services/__init__.py
src/services/api.py
src/services/cli.py
tests/__init__.py
tests/dayatrans.py
tests/test_decrypt.py
tests/test_decrypt_redacted_sample_image.py
tests/test_decrypt_sample_image.py
tests/test_encrypt.py
tests/test_encrypt_images.py
tests/test_encrypt_workflow.py
tests/test_generate_key.py
tests/test_load_pii_config.py
redactCREW-1.0.0.dist-info/METADATA
redactCREW-1.0.0.dist-info/WHEEL
redactCREW-1.0.0.dist-info/top_level.txt
redactCREW-1.0.0.dist-info/RECORD
