Metadata-Version: 2.1
Name: redactCREW
Version: 1.0.0
Summary: A package for PII redaction, encryption, and OCR workflows.
Home-page: https://github.com/dhayeah7/redactCREW
Author: redactcrew
Author-email: rmdvcbe9@gmail.com
Classifier: Programming Language :: Python :: 3
Classifier: License :: OSI Approved :: MIT License
Classifier: Operating System :: OS Independent
Requires-Python: >=3.6
Requires-Dist: pytesseract
Requires-Dist: Pillow
Requires-Dist: spacy
Requires-Dist: spacy-transformers
Requires-Dist: cryptography
Requires-Dist: PyYAML
Requires-Dist: python-magic
Requires-Dist: requests
Requires-Dist: tqdm
Requires-Dist: fastapi
Requires-Dist: uvicorn
Requires-Dist: pytest
Requires-Dist: pytest-cov
Requires-Dist: black
Requires-Dist: flake8
Requires-Dist: loguru
Requires-Dist: pymupdf
Requires-Dist: easyocr
Requires-Dist: transformers
Requires-Dist: torch
Requires-Dist: pdf2image
Requires-Dist: PyMuPDF
